[{"article":"Tabla periódica de los elementos","views":9376450,"mobile_percentage":42.58,"rank":1},{"article":"Pandemia de enfermedad por coronavirus de 2019-2020","views":9344185,"mobile_percentage":65.33,"rank":2},{"article":"COVID-19","views":8634434,"mobile_percentage":62.89,"rank":3},{"article":"Isabel II del Reino Unido","views":6839045,"mobile_percentage":87.79,"rank":4},{"article":"Cleopatra","views":6517718,"mobile_percentage":97.08,"rank":5},{"article":"Peste negra","views":6237316,"mobile_percentage":78.77,"rank":6},{"article":"Zodiaco","views":6121453,"mobile_percentage":89.82,"rank":7},{"article":"Pandemia de gripe de 1918","views":4879581,"mobile_percentage":80.1,"rank":8},{"article":"Primera Guerra Mundial","views":4831899,"mobile_percentage":70.56,"rank":9},{"article":"Segunda Guerra Mundial","views":4633989,"mobile_percentage":67.23,"rank":10},{"article":"Diego Maradona","views":4250823,"mobile_percentage":81.17,"rank":11},{"article":"Estados Unidos","views":4190214,"mobile_percentage":69.61,"rank":12},{"article":"Arroba (símbolo)","views":4118110,"mobile_percentage":3.45,"rank":13},{"article":"Lali Espósito","views":4095972,"mobile_percentage":6.83,"rank":14},{"article":"Facebook","views":4007255,"mobile_percentage":38.66,"rank":15},{"article":"YouTube","views":4001369,"mobile_percentage":32.04,"rank":16},{"article":"Coronavirus","views":3832449,"mobile_percentage":85.59,"rank":17},{"article":"España","views":3824360,"mobile_percentage":66.92,"rank":18},{"article":"Kobe Bryant","views":3823812,"mobile_percentage":84.97,"rank":19},{"article":"Freddie Mercury","views":3756629,"mobile_percentage":85.93,"rank":20},{"article":"Revolución Industrial","views":3619458,"mobile_percentage":61.11,"rank":21},{"article":"Joe Biden","views":3555398,"mobile_percentage":80.32,"rank":22},{"article":"Donald Trump","views":3484979,"mobile_percentage":76.95,"rank":23},{"article":"Zodiaco occidental","views":3300690,"mobile_percentage":92.41,"rank":24},{"article":"Virus","views":3207548,"mobile_percentage":67.11,"rank":25},{"article":"Pablo Escobar","views":3180062,"mobile_percentage":86.74,"rank":26},{"article":"Leyes de Newton","views":3058651,"mobile_percentage":62.71,"rank":27},{"article":"México","views":3046338,"mobile_percentage":67.33,"rank":28},{"article":"Michael Jordan","views":3020968,"mobile_percentage":82.41,"rank":29},{"article":"Selena","views":3001882,"mobile_percentage":87.88,"rank":30},{"article":"SARS-CoV-2","views":2994468,"mobile_percentage":67.89,"rank":31},{"article":"Traducción","views":2986175,"mobile_percentage":29.22,"rank":32},{"article":"Margarita del Reino Unido","views":2975276,"mobile_percentage":91.44,"rank":33},{"article":"Accidente de Chernóbil","views":2965249,"mobile_percentage":80.88,"rank":34},{"article":"Frida Kahlo","views":2897957,"mobile_percentage":75.04,"rank":35},{"article":"Felipe de Edimburgo","views":2834901,"mobile_percentage":89.8,"rank":36},{"article":"Lionel Messi","views":2799176,"mobile_percentage":75.83,"rank":37},{"article":"Cultura maya","views":2797550,"mobile_percentage":67.82,"rank":38},{"article":"Descubrimiento de América","views":2752007,"mobile_percentage":73.1,"rank":39},{"article":"Dark (serie de televisión)","views":2692709,"mobile_percentage":78.62,"rank":40},{"article":"Elecciones presidenciales de Estados Unidos de 2020","views":2690177,"mobile_percentage":68.88,"rank":41},{"article":"Guerra Fría","views":2683891,"mobile_percentage":61.85,"rank":42},{"article":"Adolf Hitler","views":2676217,"mobile_percentage":71.54,"rank":43},{"article":"La casa de papel","views":2668470,"mobile_percentage":74.48,"rank":44},{"article":"Cristiano Ronaldo","views":2649386,"mobile_percentage":79.37,"rank":45},{"article":"Diana de Gales","views":2647273,"mobile_percentage":86.7,"rank":46},{"article":"Argentina","views":2574811,"mobile_percentage":67.46,"rank":47},{"article":"Simón Bolívar","views":2563159,"mobile_percentage":71.44,"rank":48},{"article":"Revolución francesa","views":2559779,"mobile_percentage":60.39,"rank":49},{"article":"Stephen Hawking","views":2547711,"mobile_percentage":81.58,"rank":50},{"article":"Método científico","views":2531473,"mobile_percentage":58.38,"rank":51},{"article":"Baloncesto","views":2529559,"mobile_percentage":60.19,"rank":52},{"article":"Independencia de México","views":2514707,"mobile_percentage":76.26,"rank":53},{"article":"Pandemia","views":2507962,"mobile_percentage":72.55,"rank":54},{"article":"Democracia","views":2473313,"mobile_percentage":62.99,"rank":55},{"article":"Gmail","views":2445857,"mobile_percentage":25.2,"rank":56},{"article":"Liga de Campeones de la UEFA","views":2346723,"mobile_percentage":71.02,"rank":57},{"article":"Albert Einstein","views":2338499,"mobile_percentage":68.29,"rank":58},{"article":"RT","views":2321788,"mobile_percentage":90.14,"rank":59},{"article":"Voleibol","views":2313937,"mobile_percentage":58.4,"rank":60},{"article":"Revolución mexicana","views":2310994,"mobile_percentage":71.07,"rank":61},{"article":"Ilustración","views":2300716,"mobile_percentage":58.87,"rank":62},{"article":"Google","views":2296619,"mobile_percentage":45.15,"rank":63},{"article":"Globalización","views":2280038,"mobile_percentage":57.52,"rank":64},{"article":"Carlos de Gales","views":2265122,"mobile_percentage":89.04,"rank":65},{"article":"Cristóbal Colón","views":2264623,"mobile_percentage":69.32,"rank":66},{"article":"Outlook (correo web)","views":2257730,"mobile_percentage":56.35,"rank":67},{"article":"Elon Musk","views":2252440,"mobile_percentage":74.47,"rank":68},{"article":"Sigmund Freud","views":2223128,"mobile_percentage":76.66,"rank":69},{"article":"Orthocoronavirinae","views":2199961,"mobile_percentage":71.09,"rank":70},{"article":"Anne with an E","views":2197105,"mobile_percentage":82.78,"rank":71},{"article":"Sistema solar","views":2192344,"mobile_percentage":68.32,"rank":72},{"article":"Colombia","views":2181175,"mobile_percentage":65.1,"rank":73},{"article":"Fernando Simón","views":2176225,"mobile_percentage":84.51,"rank":74},{"article":"Célula","views":2150638,"mobile_percentage":64.26,"rank":75},{"article":"Miguel Ángel Félix Gallardo","views":2149094,"mobile_percentage":89.6,"rank":76},{"article":"Derechos humanos","views":2140860,"mobile_percentage":71.5,"rank":77},{"article":"Jorge VI del Reino Unido","views":2138307,"mobile_percentage":88.36,"rank":78},{"article":"Renacimiento","views":2134977,"mobile_percentage":55.67,"rank":79},{"article":"Carlo Acutis","views":2117067,"mobile_percentage":84.93,"rank":80},{"article":"Jeffrey Epstein","views":2083714,"mobile_percentage":82.89,"rank":81},{"article":"Leonardo da Vinci","views":2077148,"mobile_percentage":60.58,"rank":82},{"article":"Aristóteles","views":2069205,"mobile_percentage":58.57,"rank":83},{"article":"WhatsApp","views":2059905,"mobile_percentage":28.48,"rank":84},{"article":"Billie Eilish","views":2055691,"mobile_percentage":73.99,"rank":85},{"article":"Cuarentena","views":2049309,"mobile_percentage":81.35,"rank":86},{"article":"Winston Churchill","views":1987566,"mobile_percentage":83.16,"rank":87},{"article":"Wikipedia","views":1984510,"mobile_percentage":47.81,"rank":88},{"article":"Pandemia de gripe A (H1N1) de 2009-2010","views":1970186,"mobile_percentage":75.96,"rank":89},{"article":"Virreinato de Nueva España","views":1961910,"mobile_percentage":73.21,"rank":90},{"article":"Napoleón Bonaparte","views":1950895,"mobile_percentage":67.57,"rank":91},{"article":"Manuel Belgrano","views":1946168,"mobile_percentage":75.27,"rank":92},{"article":"Brad Pitt","views":1946060,"mobile_percentage":85.93,"rank":93},{"article":"Edad Media","views":1939660,"mobile_percentage":57.03,"rank":94},{"article":"Atletismo","views":1926390,"mobile_percentage":60.6,"rank":95},{"article":"Diez Mandamientos","views":1910154,"mobile_percentage":82.1,"rank":96},{"article":"Signo zodiacal","views":1908037,"mobile_percentage":89.59,"rank":97},{"article":"Jennifer Lopez","views":1907054,"mobile_percentage":86.69,"rank":98},{"article":"Benito Juárez","views":1882444,"mobile_percentage":77.83,"rank":99},{"article":"Anya Taylor-Joy","views":1859413,"mobile_percentage":78.49,"rank":100},{"article":"Diez plagas de Egipto","views":1856495,"mobile_percentage":87.22,"rank":101},{"article":"Medio de comunicación","views":1847565,"mobile_percentage":65.89,"rank":102},{"article":"Fascismo","views":1847092,"mobile_percentage":70.51,"rank":103},{"article":"BTS (banda)","views":1830962,"mobile_percentage":69.52,"rank":104},{"article":"Deutsche Welle","views":1802827,"mobile_percentage":85.85,"rank":105},{"article":"Michael Jackson","views":1800750,"mobile_percentage":73.67,"rank":106},{"article":"Neoliberalismo","views":1799785,"mobile_percentage":59.58,"rank":107},{"article":"Discriminación","views":1798857,"mobile_percentage":68.49,"rank":108},{"article":"Martin Luther King","views":1793227,"mobile_percentage":69.43,"rank":109},{"article":"América Latina","views":1792967,"mobile_percentage":65.38,"rank":110},{"article":"Reino Unido","views":1790670,"mobile_percentage":69.83,"rank":111},{"article":"Joaquín Guzmán Loera","views":1789618,"mobile_percentage":88.65,"rank":112},{"article":"Guerra civil española","views":1787319,"mobile_percentage":70.47,"rank":113},{"article":"Tecnología","views":1782996,"mobile_percentage":55.21,"rank":114},{"article":"República Popular China","views":1782436,"mobile_percentage":67.96,"rank":115},{"article":"Constitución Política de los Estados Unidos Mexicanos","views":1774375,"mobile_percentage":68.51,"rank":116},{"article":"Kim Jong-un","views":1765542,"mobile_percentage":82.07,"rank":117},{"article":"Grey's Anatomy","views":1765031,"mobile_percentage":80.69,"rank":118},{"article":"Poblamiento de América","views":1762708,"mobile_percentage":72.74,"rank":119},{"article":"Generación Y","views":1754956,"mobile_percentage":78.15,"rank":120},{"article":"La Veneno","views":1754201,"mobile_percentage":87.26,"rank":121},{"article":"Isaac Newton","views":1753773,"mobile_percentage":61.59,"rank":122},{"article":"Joaquin Phoenix","views":1753660,"mobile_percentage":84.08,"rank":123},{"article":"Fútbol","views":1753077,"mobile_percentage":55.38,"rank":124},{"article":"José de San Martín","views":1748033,"mobile_percentage":73.51,"rank":125},{"article":"Elemento químico","views":1744008,"mobile_percentage":61.34,"rank":126},{"article":"Generación Z","views":1740910,"mobile_percentage":77.48,"rank":127},{"article":"Estado de agregación de la materia","views":1739934,"mobile_percentage":69.84,"rank":128},{"article":"Clima","views":1728787,"mobile_percentage":80.08,"rank":129},{"article":"Evaluna Montaner","views":1727197,"mobile_percentage":85.52,"rank":130},{"article":"Contaminación","views":1723008,"mobile_percentage":63.98,"rank":131},{"article":"Lana Rhoades","views":1719860,"mobile_percentage":86.01,"rank":132},{"article":"Big Bang","views":1718558,"mobile_percentage":64.83,"rank":133},{"article":"Venezuela","views":1714729,"mobile_percentage":63.4,"rank":134},{"article":"Marie Curie","views":1709761,"mobile_percentage":67.47,"rank":135},{"article":"Pecados capitales","views":1707513,"mobile_percentage":81.64,"rank":136},{"article":"Will Smith","views":1702097,"mobile_percentage":82.37,"rank":137},{"article":"Charles Darwin","views":1698136,"mobile_percentage":65.61,"rank":138},{"article":"Nuevas siete maravillas del mundo moderno","views":1697074,"mobile_percentage":85.38,"rank":139},{"article":"Átomo","views":1696101,"mobile_percentage":62.71,"rank":140},{"article":"Continente","views":1694324,"mobile_percentage":72.36,"rank":141},{"article":"Tierra","views":1691903,"mobile_percentage":67.64,"rank":142},{"article":"Parásitos (película)","views":1684684,"mobile_percentage":72.13,"rank":143},{"article":"Filosofía","views":1680516,"mobile_percentage":65.62,"rank":144},{"article":"Arcángel","views":1672280,"mobile_percentage":86.18,"rank":145},{"article":"Instagram","views":1663531,"mobile_percentage":39.41,"rank":146},{"article":"Día Internacional de la Mujer","views":1661680,"mobile_percentage":71.76,"rank":147},{"article":"Aparato digestivo","views":1660973,"mobile_percentage":66.88,"rank":148},{"article":"Karl Marx","views":1651711,"mobile_percentage":58.81,"rank":149},{"article":"Gabriel García Márquez","views":1638156,"mobile_percentage":62.09,"rank":150},{"article":"Anonymous","views":1637857,"mobile_percentage":82.75,"rank":151},{"article":"Keanu Reeves","views":1636599,"mobile_percentage":84.17,"rank":152},{"article":"Europa","views":1636068,"mobile_percentage":65.65,"rank":153},{"article":"Leonardo DiCaprio","views":1623588,"mobile_percentage":83.65,"rank":154},{"article":"Ester Expósito","views":1620395,"mobile_percentage":86.14,"rank":155},{"article":"Dua Lipa","views":1615638,"mobile_percentage":74.23,"rank":156},{"article":"Peaky Blinders","views":1615048,"mobile_percentage":77.88,"rank":157},{"article":"Élite (serie de televisión)","views":1610306,"mobile_percentage":75.75,"rank":158},{"article":"Recurso natural","views":1609027,"mobile_percentage":70.27,"rank":159},{"article":"Francisco (papa)","views":1606270,"mobile_percentage":80.53,"rank":160},{"article":"Shakira","views":1605061,"mobile_percentage":77.3,"rank":161},{"article":"Amado Carrillo","views":1602285,"mobile_percentage":90.32,"rank":162},{"article":"Nuevo Orden Mundial (conspiración)","views":1601220,"mobile_percentage":83.08,"rank":163},{"article":"TikTok","views":1597636,"mobile_percentage":66.59,"rank":164},{"article":"Gran Depresión","views":1597377,"mobile_percentage":61.29,"rank":165},{"article":"Aparato respiratorio","views":1592261,"mobile_percentage":64.73,"rank":166},{"article":"Atentados del 11 de septiembre de 2001","views":1590244,"mobile_percentage":75.36,"rank":167},{"article":"LeBron James","views":1589457,"mobile_percentage":82.43,"rank":168},{"article":"Conquista de México","views":1589091,"mobile_percentage":73.57,"rank":169},{"article":"Agencia Pública Empresarial de la Radio Televisión de Andalucía","views":1579241,"mobile_percentage":94.93,"rank":170},{"article":"Ragnar Lodbrok","views":1577265,"mobile_percentage":86.48,"rank":171},{"article":"Mark Zuckerberg","views":1574023,"mobile_percentage":46.24,"rank":172},{"article":"Mesoamérica","views":1572169,"mobile_percentage":73.73,"rank":173},{"article":"Ensayo","views":1569706,"mobile_percentage":61.85,"rank":174},{"article":"Italia","views":1568743,"mobile_percentage":67.74,"rank":175},{"article":"Homo sapiens","views":1568314,"mobile_percentage":65.82,"rank":176},{"article":"Gambito de dama (miniserie)","views":1564601,"mobile_percentage":78.79,"rank":177},{"article":"Televisión Nacional de Chile","views":1563385,"mobile_percentage":93.87,"rank":178},{"article":"Cuento","views":1562636,"mobile_percentage":72.27,"rank":179},{"article":"Chadwick Boseman","views":1560298,"mobile_percentage":86.64,"rank":180},{"article":"Aparato circulatorio","views":1553685,"mobile_percentage":62.85,"rank":181},{"article":"Liberalismo","views":1551462,"mobile_percentage":64.21,"rank":182},{"article":"Familia","views":1547431,"mobile_percentage":63.15,"rank":183},{"article":"Evolución humana","views":1546204,"mobile_percentage":67.74,"rank":184},{"article":"Revolución de Mayo","views":1542705,"mobile_percentage":74.87,"rank":185},{"article":"Netflix","views":1542114,"mobile_percentage":37.65,"rank":186},{"article":"Salvador Illa","views":1541672,"mobile_percentage":85.96,"rank":187},{"article":"Bacteria","views":1541004,"mobile_percentage":62.13,"rank":188},{"article":"Conquista de América","views":1538791,"mobile_percentage":68.84,"rank":189},{"article":"Najwa Nimri","views":1530568,"mobile_percentage":85.37,"rank":190},{"article":"Peste bubónica","views":1528267,"mobile_percentage":76.39,"rank":191},{"article":"Margaret Thatcher","views":1526184,"mobile_percentage":82.09,"rank":192},{"article":"América","views":1525293,"mobile_percentage":67.76,"rank":193},{"article":"Platón","views":1522063,"mobile_percentage":58.17,"rank":194},{"article":"Bill Gates","views":1521012,"mobile_percentage":71.86,"rank":195},{"article":"Historia","views":1513184,"mobile_percentage":65.95,"rank":196},{"article":"Ana de Armas","views":1509481,"mobile_percentage":84.53,"rank":197},{"article":"Porfirio Díaz","views":1505536,"mobile_percentage":72.66,"rank":198},{"article":"Ana Frank","views":1502403,"mobile_percentage":76.03,"rank":199},{"article":"Eduardo VIII del Reino Unido","views":1501362,"mobile_percentage":88.26,"rank":200},{"article":"Harry Potter (serie cinematográfica)","views":1500056,"mobile_percentage":76.34,"rank":201},{"article":"Ludwig van Beethoven","views":1499172,"mobile_percentage":59.77,"rank":202},{"article":"Comunicación","views":1497826,"mobile_percentage":57.92,"rank":203},{"article":"Biodiversidad","views":1496396,"mobile_percentage":64.27,"rank":204},{"article":"Propiedades intensivas y extensivas","views":1493223,"mobile_percentage":63.13,"rank":205},{"article":"Unión Soviética","views":1492753,"mobile_percentage":67.81,"rank":206},{"article":"Rafael Nadal","views":1492416,"mobile_percentage":79.3,"rank":207},{"article":"Jennifer Aniston","views":1489283,"mobile_percentage":87.33,"rank":208},{"article":"Pornografía","views":1484357,"mobile_percentage":89.91,"rank":209},{"article":"Dwayne Johnson","views":1480096,"mobile_percentage":84.17,"rank":210},{"article":"Andrés Manuel López Obrador","views":1479791,"mobile_percentage":76.1,"rank":211},{"article":"Ciudad de México","views":1477726,"mobile_percentage":69.6,"rank":212},{"article":"Pablo Picasso","views":1467326,"mobile_percentage":65.48,"rank":213},{"article":"Producto interno bruto","views":1466144,"mobile_percentage":56,"rank":214},{"article":"Cuerpo humano","views":1463198,"mobile_percentage":71.49,"rank":215},{"article":"Canadá","views":1463001,"mobile_percentage":66.67,"rank":216},{"article":"Reacción química","views":1462191,"mobile_percentage":64.65,"rank":217},{"article":"Alemania","views":1460979,"mobile_percentage":63.51,"rank":218},{"article":"Victoria del Reino Unido","views":1460634,"mobile_percentage":83.4,"rank":219},{"article":"Colonización española de América","views":1455078,"mobile_percentage":67.81,"rank":220},{"article":"Copa Libertadores 2020","views":1451450,"mobile_percentage":58.58,"rank":221},{"article":"Francia","views":1450151,"mobile_percentage":63.77,"rank":222},{"article":"Kim Kardashian","views":1449330,"mobile_percentage":87.8,"rank":223},{"article":"Diomedes Díaz","views":1448236,"mobile_percentage":87.58,"rank":224},{"article":"Queen","views":1446886,"mobile_percentage":75.18,"rank":225},{"article":"Sistema endocrino","views":1444546,"mobile_percentage":65.28,"rank":226},{"article":"Guerra de Vietnam","views":1441623,"mobile_percentage":69.74,"rank":227},{"article":"Sylvester Stallone","views":1441441,"mobile_percentage":87.67,"rank":228},{"article":"Perú","views":1439441,"mobile_percentage":58.64,"rank":229},{"article":"Rusia","views":1438101,"mobile_percentage":67.02,"rank":230},{"article":"Esqueleto humano","views":1428399,"mobile_percentage":66.42,"rank":231},{"article":"Internet","views":1424644,"mobile_percentage":51.08,"rank":232},{"article":"Scarlett Johansson","views":1424139,"mobile_percentage":83.36,"rank":233},{"article":"Sócrates","views":1423837,"mobile_percentage":60.17,"rank":234},{"article":"Miguel de Cervantes","views":1420456,"mobile_percentage":63.26,"rank":235},{"article":"Danna Paola","views":1419323,"mobile_percentage":84.12,"rank":236},{"article":"Star Wars","views":1418666,"mobile_percentage":63.42,"rank":237},{"article":"Agua","views":1418489,"mobile_percentage":59.9,"rank":238},{"article":"Galileo Galilei","views":1417645,"mobile_percentage":61.35,"rank":239},{"article":"The Good Doctor","views":1416905,"mobile_percentage":78.14,"rank":240},{"article":"Nueva York","views":1414905,"mobile_percentage":69.74,"rank":241},{"article":"Sistema Internacional de Unidades","views":1413074,"mobile_percentage":53.75,"rank":242},{"article":"Guerra de las Malvinas","views":1412660,"mobile_percentage":73.39,"rank":243},{"article":"Barack Obama","views":1411323,"mobile_percentage":71.52,"rank":244},{"article":"Kylie Jenner","views":1401326,"mobile_percentage":87.92,"rank":245},{"article":"Estado socialista","views":1397297,"mobile_percentage":73.71,"rank":246},{"article":"Teorema de Pitágoras","views":1394720,"mobile_percentage":62.1,"rank":247},{"article":"Fútbol Club Barcelona","views":1391506,"mobile_percentage":70.89,"rank":248},{"article":"Chile","views":1390164,"mobile_percentage":61.85,"rank":249},{"article":"Shingeki no Kyojin","views":1388079,"mobile_percentage":67.38,"rank":250},{"article":"Nayib Bukele","views":1386442,"mobile_percentage":84.94,"rank":251},{"article":"Vladímir Putin","views":1383962,"mobile_percentage":78.01,"rank":252},{"article":"The Walking Dead (serie de televisión)","views":1383560,"mobile_percentage":74.36,"rank":253},{"article":"Luis Miguel","views":1382645,"mobile_percentage":82.36,"rank":254},{"article":"Alejandro Magno","views":1381612,"mobile_percentage":68.72,"rank":255},{"article":"Trece Colonias","views":1376252,"mobile_percentage":69.78,"rank":256},{"article":"Cambio de estado","views":1375605,"mobile_percentage":69.29,"rank":257},{"article":"Estado","views":1373412,"mobile_percentage":60.07,"rank":258},{"article":"Organización de las Naciones Unidas","views":1372655,"mobile_percentage":58.91,"rank":259},{"article":"Nikola Tesla","views":1372487,"mobile_percentage":68.62,"rank":260},{"article":"Naruto","views":1368802,"mobile_percentage":72.06,"rank":261},{"article":"Bad Bunny","views":1368734,"mobile_percentage":74.5,"rank":262},{"article":"Jesús de Nazaret","views":1363008,"mobile_percentage":71.76,"rank":263},{"article":"Idioma español","views":1359918,"mobile_percentage":66.1,"rank":264},{"article":"Johnny Depp","views":1359777,"mobile_percentage":81.97,"rank":265},{"article":"Leyes de Mendel","views":1359751,"mobile_percentage":60.49,"rank":266},{"article":"Feudalismo","views":1357563,"mobile_percentage":58.65,"rank":267},{"article":"Pasión de gavilanes","views":1357112,"mobile_percentage":86.06,"rank":268},{"article":"Aidan Gallagher","views":1356834,"mobile_percentage":84.51,"rank":269},{"article":"BDSM","views":1353212,"mobile_percentage":85.48,"rank":270},{"article":"Ricardo Montaner","views":1351699,"mobile_percentage":86.51,"rank":271},{"article":"Vikings (serie de televisión)","views":1349968,"mobile_percentage":75.86,"rank":272},{"article":"Amazon","views":1349925,"mobile_percentage":32.93,"rank":273},{"article":"Cristianismo","views":1348828,"mobile_percentage":64.53,"rank":274},{"article":"Sistema nervioso","views":1342283,"mobile_percentage":64.31,"rank":275},{"article":"Química","views":1342010,"mobile_percentage":66.7,"rank":276},{"article":"Día de Muertos","views":1339042,"mobile_percentage":67.52,"rank":277},{"article":"Ecosistema","views":1338527,"mobile_percentage":60.22,"rank":278},{"article":"Kamala Harris","views":1336568,"mobile_percentage":81.95,"rank":279},{"article":"Imperio romano","views":1327183,"mobile_percentage":65.42,"rank":280},{"article":"Número natural","views":1327070,"mobile_percentage":67.17,"rank":281},{"article":"Ciencia","views":1323458,"mobile_percentage":56.98,"rank":282},{"article":"Mito","views":1317987,"mobile_percentage":66.23,"rank":283},{"article":"Ética","views":1317378,"mobile_percentage":58,"rank":284},{"article":"Dióxido de cloro","views":1311770,"mobile_percentage":80.96,"rank":285},{"article":"Pandemia de enfermedad por coronavirus de 2020 en Perú","views":1311315,"mobile_percentage":51.81,"rank":286},{"article":"Wikipedia en español","views":1309941,"mobile_percentage":58.98,"rank":287},{"article":"Dioses olímpicos","views":1308047,"mobile_percentage":72.08,"rank":288},{"article":"Computadora","views":1306042,"mobile_percentage":51.95,"rank":289},{"article":"Aniversario de bodas","views":1305984,"mobile_percentage":88.88,"rank":290},{"article":"Lilit","views":1304566,"mobile_percentage":85.34,"rank":291},{"article":"Mezcla","views":1303746,"mobile_percentage":70.25,"rank":292},{"article":"Mesopotamia","views":1301669,"mobile_percentage":62.13,"rank":293},{"article":"Mahatma Gandhi","views":1297523,"mobile_percentage":63.39,"rank":294},{"article":"Heath Ledger","views":1296918,"mobile_percentage":87.45,"rank":295},{"article":"Derecho","views":1296710,"mobile_percentage":61.11,"rank":296},{"article":"Iglesia católica","views":1295769,"mobile_percentage":67.87,"rank":297},{"article":"Nelson Mandela","views":1294585,"mobile_percentage":63.93,"rank":298},{"article":"Bombardeos atómicos de Hiroshima y Nagasaki","views":1285787,"mobile_percentage":71.07,"rank":299},{"article":"Capitalismo","views":1285420,"mobile_percentage":60.66,"rank":300},{"article":"Número entero","views":1284877,"mobile_percentage":59.87,"rank":301},{"article":"Nanatsu no Taizai","views":1283461,"mobile_percentage":73.76,"rank":302},{"article":"Jhon Jairo Velásquez","views":1283425,"mobile_percentage":87.07,"rank":303},{"article":"Vis a vis (serie de televisión)","views":1283037,"mobile_percentage":80.24,"rank":304},{"article":"Arte","views":1279989,"mobile_percentage":63.23,"rank":305},{"article":"Harry Styles","views":1274579,"mobile_percentage":76.41,"rank":306},{"article":"Harry Potter","views":1272670,"mobile_percentage":67.05,"rank":307},{"article":"Millie Bobby Brown","views":1272580,"mobile_percentage":81.2,"rank":308},{"article":"Ariana Grande","views":1272275,"mobile_percentage":74.7,"rank":309},{"article":"Mia Khalifa","views":1269158,"mobile_percentage":85.93,"rank":310},{"article":"Biblia","views":1268146,"mobile_percentage":70.26,"rank":311},{"article":"Wolfgang Amadeus Mozart","views":1267409,"mobile_percentage":61.32,"rank":312},{"article":"Ácido desoxirribonucleico","views":1260625,"mobile_percentage":60,"rank":313},{"article":"Australia","views":1260433,"mobile_percentage":68.7,"rank":314},{"article":"RMS Titanic","views":1257601,"mobile_percentage":81.6,"rank":315},{"article":"Amber Heard","views":1256147,"mobile_percentage":84.91,"rank":316},{"article":"Canal 11 (México)","views":1255958,"mobile_percentage":90.79,"rank":317},{"article":"Ken Miles","views":1253991,"mobile_percentage":87.96,"rank":318},{"article":"Jason Statham","views":1252872,"mobile_percentage":87.72,"rank":319},{"article":"Elvis Presley","views":1250093,"mobile_percentage":77.32,"rank":320},{"article":"Ted Bundy","views":1249408,"mobile_percentage":84.75,"rank":321},{"article":"Cadena trófica","views":1245780,"mobile_percentage":72.75,"rank":322},{"article":"Charles Manson","views":1243284,"mobile_percentage":82.49,"rank":323},{"article":"Movimiento (física)","views":1242949,"mobile_percentage":65.8,"rank":324},{"article":"Google Chrome","views":1242707,"mobile_percentage":13.48,"rank":325},{"article":"India","views":1242583,"mobile_percentage":66.92,"rank":326},{"article":"Judaísmo","views":1242325,"mobile_percentage":69.42,"rank":327},{"article":"Buenos Aires","views":1241639,"mobile_percentage":58.73,"rank":328},{"article":"Madrid","views":1239810,"mobile_percentage":60.46,"rank":329},{"article":"John F. Kennedy","views":1239214,"mobile_percentage":75.03,"rank":330},{"article":"Definición","views":1237347,"mobile_percentage":77.04,"rank":331},{"article":"Luna","views":1237324,"mobile_percentage":71.21,"rank":332},{"article":"Pansexualidad","views":1236356,"mobile_percentage":83.33,"rank":333},{"article":"Holocausto","views":1233614,"mobile_percentage":68.98,"rank":334},{"article":"Brasil","views":1232603,"mobile_percentage":63.46,"rank":335},{"article":"Margot Robbie","views":1232233,"mobile_percentage":83.46,"rank":336},{"article":"Cameron Boyce","views":1231823,"mobile_percentage":88.11,"rank":337},{"article":"William Shakespeare","views":1230333,"mobile_percentage":63.43,"rank":338},{"article":"Pizzagate","views":1226607,"mobile_percentage":80.55,"rank":339},{"article":"Mapa conceptual","views":1226452,"mobile_percentage":64.66,"rank":340},{"article":"Camila de Cornualles","views":1223735,"mobile_percentage":90.75,"rank":341},{"article":"Países Bajos","views":1222184,"mobile_percentage":65.26,"rank":342},{"article":"The Mandalorian","views":1220689,"mobile_percentage":69.75,"rank":343},{"article":"Cultura","views":1217082,"mobile_percentage":63.85,"rank":344},{"article":"Puerto Rico","views":1215031,"mobile_percentage":72.42,"rank":345},{"article":"Vincent van Gogh","views":1209679,"mobile_percentage":65.67,"rank":346},{"article":"Ser vivo","views":1209231,"mobile_percentage":73.9,"rank":347},{"article":"Partido Demócrata (Estados Unidos)","views":1207460,"mobile_percentage":75.92,"rank":348},{"article":"Omegle","views":1204304,"mobile_percentage":78.12,"rank":349},{"article":"Ed y Lorraine Warren","views":1201514,"mobile_percentage":86.65,"rank":350},{"article":"Mapa mental","views":1201213,"mobile_percentage":60.05,"rank":351},{"article":"Yo soy Betty, la fea","views":1200857,"mobile_percentage":80.73,"rank":352},{"article":"Lady Gaga","views":1200706,"mobile_percentage":78.74,"rank":353},{"article":"República Dominicana","views":1199862,"mobile_percentage":70.3,"rank":354},{"article":"Isabel Díaz Ayuso","views":1198938,"mobile_percentage":81.89,"rank":355},{"article":"Evolución biológica","views":1195192,"mobile_percentage":63.04,"rank":356},{"article":"Henry Cavill","views":1191009,"mobile_percentage":84.76,"rank":357},{"article":"Rosario (catolicismo)","views":1190648,"mobile_percentage":85.6,"rank":358},{"article":"Robin Williams","views":1189849,"mobile_percentage":85.12,"rank":359},{"article":"Sean Connery","views":1189579,"mobile_percentage":83.71,"rank":360},{"article":"Ku Klux Klan","views":1188065,"mobile_percentage":74.75,"rank":361},{"article":"Francisco Franco","views":1187572,"mobile_percentage":70.55,"rank":362},{"article":"Benedicto XVI","views":1187208,"mobile_percentage":84.92,"rank":363},{"article":"Nutrición","views":1185479,"mobile_percentage":65.51,"rank":364},{"article":"Che Guevara","views":1182879,"mobile_percentage":72.88,"rank":365},{"article":"Edad Moderna","views":1181997,"mobile_percentage":58.88,"rank":366},{"article":"Viruela","views":1180993,"mobile_percentage":66.21,"rank":367},{"article":"Calentamiento global","views":1180864,"mobile_percentage":54.59,"rank":368},{"article":"Moisés","views":1179387,"mobile_percentage":77.3,"rank":369},{"article":"Jeff Bezos","views":1179346,"mobile_percentage":72.5,"rank":370},{"article":"Bruce Lee","views":1179115,"mobile_percentage":84.83,"rank":371},{"article":"Real Madrid Club de Fútbol","views":1178131,"mobile_percentage":70.49,"rank":372},{"article":"Timothée Chalamet","views":1177350,"mobile_percentage":81.99,"rank":373},{"article":"Población mundial","views":1176911,"mobile_percentage":66.28,"rank":374},{"article":"Ecuador","views":1176693,"mobile_percentage":61.84,"rank":375},{"article":"Primera División de España","views":1176442,"mobile_percentage":68.94,"rank":376},{"article":"Nostradamus","views":1175737,"mobile_percentage":84.39,"rank":377},{"article":"Tom Cruise","views":1175485,"mobile_percentage":84.52,"rank":378},{"article":"Asia","views":1175057,"mobile_percentage":66.56,"rank":379},{"article":"Creacionismo","views":1173771,"mobile_percentage":61.71,"rank":380},{"article":"Número primo","views":1173039,"mobile_percentage":66.77,"rank":381},{"article":"Ciclo hidrológico","views":1172514,"mobile_percentage":69.82,"rank":382},{"article":"Magnitud física","views":1171314,"mobile_percentage":61.71,"rank":383},{"article":"The Crown (serie de televisión)","views":1171242,"mobile_percentage":80.45,"rank":384},{"article":"Socialismo","views":1170914,"mobile_percentage":62.32,"rank":385},{"article":"Música","views":1169871,"mobile_percentage":60.37,"rank":386},{"article":"Nomenclatura química de los compuestos inorgánicos","views":1168126,"mobile_percentage":53.24,"rank":387},{"article":"Clint Eastwood","views":1168105,"mobile_percentage":82.45,"rank":388},{"article":"Modelo atómico de Bohr","views":1167965,"mobile_percentage":58.22,"rank":389},{"article":"Pelé","views":1167686,"mobile_percentage":80.64,"rank":390},{"article":"Steve Jobs","views":1162392,"mobile_percentage":65.03,"rank":391},{"article":"Canserbero","views":1160088,"mobile_percentage":79.74,"rank":392},{"article":"Riverdale (serie de televisión)","views":1157244,"mobile_percentage":75.24,"rank":393},{"article":"Piratas del Caribe","views":1157169,"mobile_percentage":78.44,"rank":394},{"article":"Administración","views":1156904,"mobile_percentage":55.88,"rank":395},{"article":"Eugenio Derbez","views":1155672,"mobile_percentage":87.47,"rank":396},{"article":"Paul Walker","views":1151097,"mobile_percentage":88.74,"rank":397},{"article":"Leyenda","views":1150408,"mobile_percentage":71.14,"rank":398},{"article":"Digestión","views":1150321,"mobile_percentage":70.43,"rank":399},{"article":"Desastre natural","views":1149142,"mobile_percentage":69.69,"rank":400},{"article":"The Beatles","views":1145785,"mobile_percentage":64.32,"rank":401},{"article":"Google Classroom","views":1145213,"mobile_percentage":28.56,"rank":402},{"article":"Pandemia de enfermedad por coronavirus de 2020 en México","views":1145098,"mobile_percentage":59.83,"rank":403},{"article":"Islam","views":1144511,"mobile_percentage":62.45,"rank":404},{"article":"Silvia Pinal","views":1141642,"mobile_percentage":92.19,"rank":405},{"article":"Zlatan Ibrahimović","views":1140527,"mobile_percentage":84.16,"rank":406},{"article":"Stranger Things","views":1140172,"mobile_percentage":69.97,"rank":407},{"article":"Olmeca","views":1137636,"mobile_percentage":68.21,"rank":408},{"article":"Ivermectina","views":1137387,"mobile_percentage":86.5,"rank":409},{"article":"Imperio azteca","views":1135264,"mobile_percentage":63.27,"rank":410},{"article":"2020","views":1135094,"mobile_percentage":62.71,"rank":411},{"article":"Adam Sandler","views":1133882,"mobile_percentage":82.47,"rank":412},{"article":"Angelina Jolie","views":1131463,"mobile_percentage":85.96,"rank":413},{"article":"Isabel I de Inglaterra","views":1131003,"mobile_percentage":81.59,"rank":414},{"article":"América del Sur","views":1130723,"mobile_percentage":65.77,"rank":415},{"article":"Fotosíntesis","views":1130538,"mobile_percentage":61.86,"rank":416},{"article":"Cayetana Álvarez de Toledo","views":1129307,"mobile_percentage":81.96,"rank":417},{"article":"Biología","views":1127099,"mobile_percentage":66.33,"rank":418},{"article":"Célula procariota","views":1127084,"mobile_percentage":60.96,"rank":419},{"article":"Densidad","views":1126057,"mobile_percentage":52.42,"rank":420},{"article":"Hernán Cortés","views":1125318,"mobile_percentage":71.06,"rank":421},{"article":"Pirámide de Maslow","views":1123859,"mobile_percentage":51.47,"rank":422},{"article":"Remdesivir","views":1121501,"mobile_percentage":81.88,"rank":423},{"article":"Felis silvestris catus","views":1118911,"mobile_percentage":70.58,"rank":424},{"article":"Copa Mundial de Fútbol","views":1118584,"mobile_percentage":69.45,"rank":425},{"article":"Turquía","views":1117992,"mobile_percentage":72.62,"rank":426},{"article":"Coordenadas cartesianas","views":1115282,"mobile_percentage":71.41,"rank":427},{"article":"Don Quijote de la Mancha","views":1113573,"mobile_percentage":58.49,"rank":428},{"article":"Japón","views":1112124,"mobile_percentage":61.72,"rank":429},{"article":"Marilyn Monroe","views":1111736,"mobile_percentage":82,"rank":430},{"article":"Antiguo Egipto","views":1110121,"mobile_percentage":62.37,"rank":431},{"article":"Imperio otomano","views":1109052,"mobile_percentage":71.84,"rank":432},{"article":"Carlos I de España","views":1107709,"mobile_percentage":64.49,"rank":433},{"article":"Estado de alarma","views":1103898,"mobile_percentage":75.55,"rank":434},{"article":"Comunismo","views":1103629,"mobile_percentage":68.21,"rank":435},{"article":"Enrique de Sussex","views":1102557,"mobile_percentage":88.26,"rank":436},{"article":"Selección natural","views":1102345,"mobile_percentage":62.27,"rank":437},{"article":"Juan Carlos I de España","views":1102218,"mobile_percentage":78.25,"rank":438},{"article":"Luis XIV de Francia","views":1101897,"mobile_percentage":76.04,"rank":439},{"article":"Pedro Sánchez","views":1101739,"mobile_percentage":77.77,"rank":440},{"article":"Sor Juana Inés de la Cruz","views":1100602,"mobile_percentage":68.26,"rank":441},{"article":"Género literario","views":1099416,"mobile_percentage":63.03,"rank":442},{"article":"Sol","views":1098650,"mobile_percentage":64.23,"rank":443},{"article":"Física","views":1098502,"mobile_percentage":66.16,"rank":444},{"article":"Reformas borbónicas en Nueva España","views":1096369,"mobile_percentage":67.51,"rank":445},{"article":"Belinda (cantante)","views":1093855,"mobile_percentage":87.87,"rank":446},{"article":"Temperatura","views":1093545,"mobile_percentage":62.15,"rank":447},{"article":"Roblox","views":1093460,"mobile_percentage":28.32,"rank":448},{"article":"Las chicas del cable","views":1091155,"mobile_percentage":81.64,"rank":449},{"article":"Breaking Bad","views":1089284,"mobile_percentage":75.68,"rank":450},{"article":"Singapur","views":1089263,"mobile_percentage":69.85,"rank":451},{"article":"Traductor de Google","views":1088811,"mobile_percentage":62.26,"rank":452},{"article":"Estado de los Estados Unidos","views":1088734,"mobile_percentage":77.79,"rank":453},{"article":"Cobra Kai","views":1087144,"mobile_percentage":78.73,"rank":454},{"article":"Materia","views":1085534,"mobile_percentage":67.01,"rank":455},{"article":"Petróleo","views":1085053,"mobile_percentage":60.21,"rank":456},{"article":"Aaron Hernandez","views":1083915,"mobile_percentage":89.42,"rank":457},{"article":"Animalia","views":1082560,"mobile_percentage":52.43,"rank":458},{"article":"Iósif Stalin","views":1082308,"mobile_percentage":66.59,"rank":459},{"article":"Siglo XIX","views":1081551,"mobile_percentage":60.61,"rank":460},{"article":"Chris Hemsworth","views":1081533,"mobile_percentage":86.81,"rank":461},{"article":"Fase lunar","views":1081032,"mobile_percentage":77.83,"rank":462},{"article":"Carlos Lehder","views":1080150,"mobile_percentage":89.3,"rank":463},{"article":"Sharon Tate","views":1079174,"mobile_percentage":86.69,"rank":464},{"article":"Migración humana","views":1078503,"mobile_percentage":68.5,"rank":465},{"article":"Ronaldinho","views":1078206,"mobile_percentage":81.92,"rank":466},{"article":"John Lennon","views":1073854,"mobile_percentage":73.09,"rank":467},{"article":"África","views":1071757,"mobile_percentage":63.41,"rank":468},{"article":"Meghan de Sussex","views":1070631,"mobile_percentage":87.09,"rank":469},{"article":"Nazismo","views":1068897,"mobile_percentage":64.57,"rank":470},{"article":"Educación física","views":1063046,"mobile_percentage":66.88,"rank":471},{"article":"Friedrich Nietzsche","views":1062670,"mobile_percentage":60.26,"rank":472},{"article":"Agnosticismo","views":1062668,"mobile_percentage":80.09,"rank":473},{"article":"Juegos Olímpicos","views":1061166,"mobile_percentage":58.37,"rank":474},{"article":"La Gioconda","views":1060245,"mobile_percentage":57.12,"rank":475},{"article":"Unión Europea","views":1058139,"mobile_percentage":55.52,"rank":476},{"article":"Juan Domingo Perón","views":1058095,"mobile_percentage":66.17,"rank":477},{"article":"Suiza","views":1057594,"mobile_percentage":67.13,"rank":478},{"article":"Religión","views":1056739,"mobile_percentage":67.61,"rank":479},{"article":"Meiosis","views":1055141,"mobile_percentage":57.45,"rank":480},{"article":"Miguel Hidalgo y Costilla","views":1054378,"mobile_percentage":78.13,"rank":481},{"article":"Teoría celular","views":1051728,"mobile_percentage":60.65,"rank":482},{"article":"George Soros","views":1051112,"mobile_percentage":75.56,"rank":483},{"article":"Organización Mundial de la Salud","views":1050269,"mobile_percentage":64.1,"rank":484},{"article":"Cristo","views":1049940,"mobile_percentage":89.28,"rank":485},{"article":"Aparato reproductor masculino","views":1048751,"mobile_percentage":68.45,"rank":486},{"article":"Microscopio","views":1046761,"mobile_percentage":61.11,"rank":487},{"article":"Tini Stoessel","views":1046442,"mobile_percentage":50.06,"rank":488},{"article":"Estereotipo","views":1046320,"mobile_percentage":63.06,"rank":489},{"article":"Lucifer","views":1044507,"mobile_percentage":83.72,"rank":490},{"article":"Anne Hathaway","views":1044492,"mobile_percentage":82.72,"rank":491},{"article":"Rosalía (cantante)","views":1043635,"mobile_percentage":77,"rank":492},{"article":"Forma de gobierno","views":1043470,"mobile_percentage":63.28,"rank":493},{"article":"Francmasonería","views":1043401,"mobile_percentage":80.61,"rank":494},{"article":"Arnold Schwarzenegger","views":1042993,"mobile_percentage":82.33,"rank":495},{"article":"Charlize Theron","views":1042796,"mobile_percentage":85.16,"rank":496},{"article":"Poder ejecutivo","views":1042275,"mobile_percentage":65.79,"rank":497},{"article":"Transporte celular","views":1038727,"mobile_percentage":57.4,"rank":498},{"article":"Modelo atómico de Dalton","views":1037394,"mobile_percentage":59.89,"rank":499},{"article":"Carbono","views":1037073,"mobile_percentage":55.09,"rank":500}]